{"type":"CIMPointSymbol","symbolLayers":[{"type":"CIMVectorMarker","enable":true,"anchorPointUnits":"Relative","dominantSizeAxis3D":"Z","size":64,"billboardMode3D":"FaceNearPlane","frame":{"xmin":0,"ymin":0,"xmax":612,"ymax":792},"markerGraphics":[{"type":"CIMMarkerGraphic","geometry":{"paths":[[[306.0,438.0],[226.0,348.0],[386.0,348.0],[306.0,438.0],[306.0,505.5]]]},"symbol":{"type":"CIMPolygonSymbol","symbolLayers":[{"type":"CIMSolidStroke","enable":true,"primitiveName":"icon_element","capStyle":"Butt","joinStyle":"Miter","lineStyle3D":"Strip","miterLimit":10,"width":4.7565743412206016,"color":[0,0,0,255]}]}},{"type":"CIMMarkerGraphic","geometry":{"rings":[[[223.0,329.46],[223.25,326.93],[223.99,324.49],[225.19,322.24],[226.81,320.27],[228.78,318.65],[231.03,317.45],[233.46,316.71],[236.0,316.46],[238.54,316.71],[240.97,317.45],[243.22,318.65],[245.19,320.27],[246.81,322.24],[248.01,324.49],[248.75,326.93],[249.0,329.46],[248.75,332.0],[248.01,334.44],[246.81,336.68],[245.19,338.65],[243.22,340.27],[240.97,341.47],[238.54,342.21],[236.0,342.46],[233.46,342.21],[231.03,341.47],[228.78,340.27],[226.81,338.65],[225.19,336.68],[223.99,334.44],[223.25,332.0],[223.0,329.46]]]},"symbol":{"type":"CIMPolygonSymbol","symbolLayers":[{"type":"CIMSolidStroke","enable":true,"primitiveName":"icon_element","capStyle":"Round","joinStyle":"Miter","lineStyle3D":"Strip","miterLimit":10,"width":4.7565743412206016,"color":[0,0,0,255]}]}},{"type":"CIMMarkerGraphic","geometry":{"rings":[[[363.0,329.46],[363.25,326.93],[363.99,324.49],[365.19,322.24],[366.81,320.27],[368.78,318.65],[371.03,317.45],[373.46,316.71],[376.0,316.46],[378.54,316.71],[380.97,317.45],[383.22,318.65],[385.19,320.27],[386.81,322.24],[388.01,324.49],[388.75,326.93],[389.0,329.46],[388.75,332.0],[388.01,334.44],[386.81,336.68],[385.19,338.65],[383.22,340.27],[380.97,341.47],[378.54,342.21],[376.0,342.46],[373.46,342.21],[371.03,341.47],[368.78,340.27],[366.81,338.65],[365.19,336.68],[363.99,334.44],[363.25,332.0],[363.0,329.46]]]},"symbol":{"type":"CIMPolygonSymbol","symbolLayers":[{"type":"CIMSolidStroke","enable":true,"primitiveName":"icon_element","capStyle":"Round","joinStyle":"Miter","lineStyle3D":"Strip","miterLimit":10,"width":4.7565743412206016,"color":[0,0,0,255]}]}}],"scaleSymbolsProportionally":true,"respectFrame":true}],"haloSize":1,"scaleX":1,"angleAlignment":"Display"}