{"type":"CIMPointSymbol","symbolLayers":[{"type":"CIMVectorMarker","enable":true,"anchorPointUnits":"Relative","dominantSizeAxis3D":"Z","size":64,"billboardMode3D":"FaceNearPlane","frame":{"xmin":0,"ymin":0,"xmax":612,"ymax":792},"markerGraphics":[{"type":"CIMMarkerGraphic","geometry":{"paths":[[[227.0,463.5],[227.0,348.5]]]},"symbol":{"type":"CIMPolygonSymbol","symbolLayers":[{"type":"CIMSolidStroke","enable":true,"primitiveName":"icon_element","capStyle":"Butt","joinStyle":"Miter","lineStyle3D":"Strip","miterLimit":10,"width":5,"color":[0,0,0,255]}]}},{"type":"CIMMarkerGraphic","geometry":{"paths":[[[387.0,463.5],[387.0,348.5]]]},"symbol":{"type":"CIMPolygonSymbol","symbolLayers":[{"type":"CIMSolidStroke","enable":true,"primitiveName":"icon_element","capStyle":"Butt","joinStyle":"Miter","lineStyle3D":"Strip","miterLimit":10,"width":5,"color":[0,0,0,255]}]}},{"type":"CIMMarkerGraphic","geometry":{"paths":[[[227.0,351.5],[387.0,351.5]]]},"symbol":{"type":"CIMPolygonSymbol","symbolLayers":[{"type":"CIMSolidStroke","enable":true,"primitiveName":"icon_element","capStyle":"Butt","joinStyle":"Miter","lineStyle3D":"Strip","miterLimit":10,"width":5,"color":[0,0,0,255]}]}},{"type":"CIMMarkerGraphic","geometry":{"paths":[[[227.0,461.5],[253.4,452.2],[273.6,446.4],[291.0,443.1],[307.0,442.0],[323.0,443.1],[340.4,446.4],[360.6,452.2],[387.0,461.5]]]},"symbol":{"type":"CIMPolygonSymbol","symbolLayers":[{"type":"CIMSolidStroke","enable":true,"primitiveName":"icon_element","capStyle":"Butt","joinStyle":"Miter","lineStyle3D":"Strip","miterLimit":10,"width":5,"color":[0,0,0,255]}]}},{"type":"CIMMarkerGraphic","geometry":{"rings":[[[237.0,319.5],[239.26,319.7],[241.45,320.28],[243.5,321.24],[245.36,322.54],[246.96,324.14],[248.26,326.0],[249.22,328.05],[249.8,330.24],[250.0,332.5],[249.8,334.76],[249.22,336.95],[248.26,339.0],[246.96,340.86],[245.36,342.46],[243.5,343.76],[241.45,344.72],[239.26,345.3],[237.0,345.5],[234.74,345.3],[232.55,344.72],[230.5,343.76],[228.64,342.46],[227.04,340.86],[225.74,339.0],[224.78,336.95],[224.2,334.76],[224.0,332.5],[224.2,330.24],[224.78,328.05],[225.74,326.0],[227.04,324.14],[228.64,322.54],[230.5,321.24],[232.55,320.28],[234.74,319.7],[237.0,319.5]]]},"symbol":{"type":"CIMPolygonSymbol","symbolLayers":[{"type":"CIMSolidStroke","enable":true,"primitiveName":"icon_element","capStyle":"Round","joinStyle":"Miter","lineStyle3D":"Strip","miterLimit":10,"width":5,"color":[0,0,0,255]}]}},{"type":"CIMMarkerGraphic","geometry":{"rings":[[[307.0,319.5],[309.03,319.66],[311.02,320.14],[312.9,320.92],[314.64,321.98],[316.19,323.31],[317.52,324.86],[318.58,326.6],[319.36,328.48],[319.84,330.47],[320.0,332.5],[319.84,334.53],[319.36,336.52],[318.58,338.4],[317.52,340.14],[316.19,341.69],[314.64,343.02],[312.9,344.08],[311.02,344.86],[309.03,345.34],[307.0,345.5],[304.97,345.34],[302.98,344.86],[301.1,344.08],[299.36,343.02],[297.81,341.69],[296.48,340.14],[295.42,338.4],[294.64,336.52],[294.16,334.53],[294.0,332.5],[294.16,330.47],[294.64,328.48],[295.42,326.6],[296.48,324.86],[297.81,323.31],[299.36,321.98],[301.1,320.92],[302.98,320.14],[304.97,319.66],[307.0,319.5]]]},"symbol":{"type":"CIMPolygonSymbol","symbolLayers":[{"type":"CIMSolidStroke","enable":true,"primitiveName":"icon_element","capStyle":"Round","joinStyle":"Miter","lineStyle3D":"Strip","miterLimit":10,"width":5,"color":[0,0,0,255]}]}},{"type":"CIMMarkerGraphic","geometry":{"rings":[[[377.0,319.5],[379.03,319.66],[381.02,320.14],[382.9,320.92],[384.64,321.98],[386.19,323.31],[387.52,324.86],[388.58,326.6],[389.36,328.48],[389.84,330.47],[390.0,332.5],[389.84,334.53],[389.36,336.52],[388.58,338.4],[387.52,340.14],[386.19,341.69],[384.64,343.02],[382.9,344.08],[381.02,344.86],[379.03,345.34],[377.0,345.5],[374.97,345.34],[372.98,344.86],[371.1,344.08],[369.36,343.02],[367.81,341.69],[366.48,340.14],[365.42,338.4],[364.64,336.52],[364.16,334.53],[364.0,332.5],[364.16,330.47],[364.64,328.48],[365.42,326.6],[366.48,324.86],[367.81,323.31],[369.36,321.98],[371.1,320.92],[372.98,320.14],[374.97,319.66],[377.0,319.5]]]},"symbol":{"type":"CIMPolygonSymbol","symbolLayers":[{"type":"CIMSolidStroke","enable":true,"primitiveName":"icon_element","capStyle":"Round","joinStyle":"Miter","lineStyle3D":"Strip","miterLimit":10,"width":5,"color":[0,0,0,255]}]}},{"type":"CIMMarkerGraphic","geometry":{"rings":[[[247.0,406.5],[262.0,393.4],[277.0,384.0],[284.5,380.7],[292.0,378.4],[299.5,377.0],[307.0,376.5],[314.5,377.0],[322.0,378.4],[329.5,380.7],[337.0,384.0],[352.0,393.4],[367.0,406.5],[247.0,406.5]]]},"symbol":{"type":"CIMPolygonSymbol","symbolLayers":[{"type":"CIMSolidStroke","enable":true,"primitiveName":"icon_element","capStyle":"Round","joinStyle":"Miter","lineStyle3D":"Strip","miterLimit":10,"width":5,"color":[0,0,0,255]}]}}],"scaleSymbolsProportionally":true,"respectFrame":true}],"haloSize":1,"scaleX":1,"angleAlignment":"Display"}