{"type":"CIMPointSymbol","symbolLayers":[{"type":"CIMVectorMarker","enable":true,"anchorPointUnits":"Relative","dominantSizeAxis3D":"Z","size":64,"billboardMode3D":"FaceNearPlane","frame":{"xmin":0,"ymin":0,"xmax":612,"ymax":792},"markerGraphics":[{"type":"CIMMarkerGraphic","geometry":{"rings":[[[310,549],[335,521],[335,648],[327,648],[327,541],[303,572],[303,484],[310,484],[310,549]],[[307,315],[291,316],[276,321],[262,328],[250,338],[239,351],[232,364],[228,379],[226,396],[228,412],[232,427],[239,441],[249,453],[262,464],[275,471],[290,475],[307,477],[323,475],[338,471],[352,464],[364,453],[374,441],[382,427],[386,412],[387,396],[386,379],[382,364],[374,351],[364,338],[352,328],[338,321],[323,316],[307,315]],[[307,308],[325,310],[341,314],[356,322],[369,333],[380,347],[388,362],[393,378],[394,396],[393,413],[388,430],[380,445],[369,458],[356,469],[341,477],[324,482],[307,484],[289,482],[273,477],[258,469],[245,458],[234,445],[226,430],[221,414],[219,396],[221,378],[226,362],[234,347],[245,334],[258,322],[273,315],[289,310],[307,308]]]},"symbol":{"type":"CIMPolygonSymbol","symbolLayers":[{"type":"CIMSolidFill","enable":true,"primitiveName":"cm_color","color":[0,0,0,255]}]}},{"type":"CIMMarkerGraphic","geometry":{"paths":[[[211.8,316.4],[399.9,475.3]]]},"symbol":{"type":"CIMPolygonSymbol","symbolLayers":[{"type":"CIMSolidStroke","enable":true,"primitiveName":"cm_color","capStyle":"Butt","joinStyle":"Miter","lineStyle3D":"Strip","miterLimit":10,"width":5,"color":[0,0,0,255]}]}},{"type":"CIMMarkerGraphic","geometry":{"paths":[[[399.9,316.4],[211.8,475.3]]]},"symbol":{"type":"CIMPolygonSymbol","symbolLayers":[{"type":"CIMSolidStroke","enable":true,"primitiveName":"cm_color","capStyle":"Butt","joinStyle":"Miter","lineStyle3D":"Strip","miterLimit":10,"width":5,"color":[0,0,0,255]}]}}],"scaleSymbolsProportionally":true,"respectFrame":true}],"haloSize":1,"scaleX":1,"angleAlignment":"Display"}