{"type":"CIMPointSymbol","symbolLayers":[{"type":"CIMVectorMarker","enable":true,"anchorPointUnits":"Relative","dominantSizeAxis3D":"Z","size":84,"billboardMode3D":"FaceNearPlane","frame":{"xmin":0,"ymin":0,"xmax":612,"ymax":792},"markerGraphics":[{"type":"CIMMarkerGraphic","geometry":{"rings":[[[242.4,482.2],[370.6,482.2],[370.6,653.2],[242.4,653.2],[242.4,482.2]]]},"symbol":{"type":"CIMPolygonSymbol","symbolLayers":[{"type":"CIMSolidStroke","effects":[{"type":"CIMGeometricEffectAddControlPoints","angleTolerance":120},{"type":"CIMGeometricEffectDashes","dashTemplate":[23.571428571428573,23.571428571428573],"lineDashEnding":"FullPattern","controlPointEnding":"NoConstraint"}],"enable":true,"primitiveName":"cm_color","capStyle":"Butt","joinStyle":"Miter","lineStyle3D":"Strip","miterLimit":10,"width":4,"color":[0,0,0,255]}]}},{"type":"CIMMarkerGraphic","geometry":{"rings":[[[306.5,396.5],[242.4,482.0],[370.6,482.0],[306.5,396.5]]]},"symbol":{"type":"CIMPolygonSymbol","symbolLayers":[{"type":"CIMSolidStroke","effects":[{"type":"CIMGeometricEffectAddControlPoints","angleTolerance":120},{"type":"CIMGeometricEffectDashes","dashTemplate":[23.571428571428573,23.571428571428573],"lineDashEnding":"FullPattern","controlPointEnding":"NoConstraint"}],"enable":true,"primitiveName":"cm_color","capStyle":"Butt","joinStyle":"Miter","lineStyle3D":"Strip","miterLimit":10,"width":4,"color":[0,0,0,255]}]}},{"type":"CIMMarkerGraphic","geometry":{"paths":[[[242.4,503.7],[370.6,503.7]]]},"symbol":{"type":"CIMPolygonSymbol","symbolLayers":[{"type":"CIMSolidStroke","enable":true,"primitiveName":"cm_color","capStyle":"Butt","joinStyle":"Miter","lineStyle3D":"Strip","miterLimit":10,"width":4,"color":[0,0,0,255]}]}},{"type":"CIMMarkerGraphic","geometry":{"rings":[[[262.57,561.35],[265.15,561.61],[267.64,562.36],[269.93,563.58],[271.93,565.23],[273.58,567.24],[274.81,569.53],[275.56,572.01],[275.81,574.6],[275.56,577.18],[274.81,579.67],[273.58,581.96],[271.93,583.96],[269.93,585.61],[267.64,586.83],[265.15,587.59],[262.57,587.84],[259.98,587.59],[257.5,586.83],[255.21,585.61],[253.2,583.96],[251.55,581.96],[250.33,579.67],[249.58,577.18],[249.32,574.6],[249.58,572.01],[250.33,569.53],[251.55,567.24],[253.2,565.23],[255.21,563.58],[257.5,562.36],[259.98,561.61],[262.57,561.35]]]},"symbol":{"type":"CIMPolygonSymbol","symbolLayers":[{"type":"CIMSolidFill","enable":true,"primitiveName":"cm_color","color":[0,0,0,255]}]}},{"type":"CIMMarkerGraphic","geometry":{"rings":[[[262.57,561.35],[265.15,561.61],[267.64,562.36],[269.93,563.58],[271.93,565.23],[273.58,567.24],[274.81,569.53],[275.56,572.01],[275.81,574.6],[275.56,577.18],[274.81,579.67],[273.58,581.96],[271.93,583.96],[269.93,585.61],[267.64,586.83],[265.15,587.59],[262.57,587.84],[259.98,587.59],[257.5,586.83],[255.21,585.61],[253.2,583.96],[251.55,581.96],[250.33,579.67],[249.58,577.18],[249.32,574.6],[249.58,572.01],[250.33,569.53],[251.55,567.24],[253.2,565.23],[255.21,563.58],[257.5,562.36],[259.98,561.61],[262.57,561.35]]]},"symbol":{"type":"CIMPolygonSymbol","symbolLayers":[{"type":"CIMSolidStroke","enable":true,"primitiveName":"cm_color","capStyle":"Round","joinStyle":"Miter","lineStyle3D":"Strip","miterLimit":10,"width":6,"color":[0,0,0,255]}]}},{"type":"CIMMarkerGraphic","geometry":{"rings":[[[350.87,561.35],[353.45,561.61],[355.94,562.36],[358.23,563.58],[360.24,565.23],[361.88,567.24],[363.11,569.53],[363.86,572.01],[364.11,574.6],[363.86,577.18],[363.11,579.67],[361.88,581.96],[360.24,583.96],[358.23,585.61],[355.94,586.83],[353.45,587.59],[350.87,587.84],[348.28,587.59],[345.8,586.83],[343.51,585.61],[341.5,583.96],[339.86,581.96],[338.63,579.67],[337.88,577.18],[337.62,574.6],[337.88,572.01],[338.63,569.53],[339.86,567.24],[341.5,565.23],[343.51,563.58],[345.8,562.36],[348.28,561.61],[350.87,561.35]]]},"symbol":{"type":"CIMPolygonSymbol","symbolLayers":[{"type":"CIMSolidFill","enable":true,"primitiveName":"cm_color","color":[0,0,0,255]}]}},{"type":"CIMMarkerGraphic","geometry":{"rings":[[[350.87,561.35],[353.45,561.61],[355.94,562.36],[358.23,563.58],[360.24,565.23],[361.88,567.24],[363.11,569.53],[363.86,572.01],[364.11,574.6],[363.86,577.18],[363.11,579.67],[361.88,581.96],[360.24,583.96],[358.23,585.61],[355.94,586.83],[353.45,587.59],[350.87,587.84],[348.28,587.59],[345.8,586.83],[343.51,585.61],[341.5,583.96],[339.86,581.96],[338.63,579.67],[337.88,577.18],[337.62,574.6],[337.88,572.01],[338.63,569.53],[339.86,567.24],[341.5,565.23],[343.51,563.58],[345.8,562.36],[348.28,561.61],[350.87,561.35]]]},"symbol":{"type":"CIMPolygonSymbol","symbolLayers":[{"type":"CIMSolidStroke","enable":true,"primitiveName":"cm_color","capStyle":"Round","joinStyle":"Miter","lineStyle3D":"Strip","miterLimit":10,"width":6,"color":[0,0,0,255]}]}},{"type":"CIMMarkerGraphic","geometry":{"paths":[[[266.2,582.0],[276.0,589.1],[286.0,594.3],[296.3,597.5],[306.7,598.5],[317.1,597.5],[327.4,594.3],[337.5,589.1],[347.2,582.0]]]},"symbol":{"type":"CIMPolygonSymbol","symbolLayers":[{"type":"CIMSolidStroke","enable":true,"primitiveName":"cm_color","capStyle":"Butt","joinStyle":"Miter","lineStyle3D":"Strip","miterLimit":10,"width":6,"color":[0,0,0,255]}]}}],"scaleSymbolsProportionally":true,"respectFrame":true}],"haloSize":1,"scaleX":1,"angleAlignment":"Display"}