{"type":"CIMPointSymbol","symbolLayers":[{"type":"CIMVectorMarker","enable":true,"anchorPointUnits":"Relative","dominantSizeAxis3D":"Z","size":64,"billboardMode3D":"FaceNearPlane","frame":{"xmin":0,"ymin":0,"xmax":612,"ymax":792},"markerGraphics":[{"type":"CIMMarkerGraphic","geometry":{"paths":[[[305.0,340.0],[305.0,305.0]]]},"symbol":{"type":"CIMPolygonSymbol","symbolLayers":[{"type":"CIMSolidStroke","enable":true,"colorLocked":true,"capStyle":"Butt","joinStyle":"Miter","lineStyle3D":"Strip","miterLimit":10,"width":10,"color":[0,0,0,255]}]}},{"type":"CIMMarkerGraphic","geometry":{"paths":[[[240.0,308.0],[370.0,308.0]]]},"symbol":{"type":"CIMPolygonSymbol","symbolLayers":[{"type":"CIMSolidStroke","enable":true,"colorLocked":true,"capStyle":"Butt","joinStyle":"Miter","lineStyle3D":"Strip","miterLimit":10,"width":10,"color":[0,0,0,255]}]}},{"type":"CIMMarkerGraphic","geometry":{"rings":[[[325.0,470.0],[325.0,505.0],[285.0,505.0],[285.0,470.0],[325.0,470.0]]]},"symbol":{"type":"CIMPolygonSymbol","symbolLayers":[{"type":"CIMSolidFill","enable":true,"colorLocked":true,"color":[0,0,0,255]}]}},{"type":"CIMMarkerGraphic","geometry":{"rings":[[[285.0,470.0],[285.0,505.0],[325.0,505.0],[325.0,470.0],[285.0,470.0]]]},"symbol":{"type":"CIMPolygonSymbol","symbolLayers":[{"type":"CIMSolidStroke","enable":true,"colorLocked":true,"capStyle":"Round","joinStyle":"Miter","lineStyle3D":"Strip","miterLimit":10,"width":10,"color":[0,0,0,255]}]}},{"type":"CIMMarkerGraphic","geometry":{"rings":[[[276.1,466.2],[251.3,490.9],[223.0,462.6],[247.8,437.9],[276.1,466.2]]]},"symbol":{"type":"CIMPolygonSymbol","symbolLayers":[{"type":"CIMSolidFill","enable":true,"colorLocked":true,"color":[0,0,0,255]}]}},{"type":"CIMMarkerGraphic","geometry":{"rings":[[[247.8,437.9],[223.0,462.6],[251.3,490.9],[276.1,466.2],[247.8,437.9]]]},"symbol":{"type":"CIMPolygonSymbol","symbolLayers":[{"type":"CIMSolidStroke","enable":true,"colorLocked":true,"capStyle":"Round","joinStyle":"Miter","lineStyle3D":"Strip","miterLimit":10,"width":10,"color":[0,0,0,255]}]}},{"type":"CIMMarkerGraphic","geometry":{"rings":[[[386.3,462.8],[358.0,491.0],[333.3,466.2],[361.6,438.0],[386.3,462.8]]]},"symbol":{"type":"CIMPolygonSymbol","symbolLayers":[{"type":"CIMSolidFill","enable":true,"colorLocked":true,"color":[0,0,0,255]}]}},{"type":"CIMMarkerGraphic","geometry":{"rings":[[[333.3,466.2],[358.0,491.0],[386.3,462.8],[361.6,438.0],[333.3,466.2]]]},"symbol":{"type":"CIMPolygonSymbol","symbolLayers":[{"type":"CIMSolidStroke","enable":true,"colorLocked":true,"capStyle":"Round","joinStyle":"Miter","lineStyle3D":"Strip","miterLimit":10,"width":10,"color":[0,0,0,255]}]}},{"type":"CIMMarkerGraphic","geometry":{"rings":[[[305.0,340.0],[318.7,341.3],[331.8,345.3],[343.9,351.8],[354.5,360.5],[363.2,371.1],[369.7,383.2],[373.7,396.3],[375.0,410.0],[373.7,423.7],[369.7,436.8],[363.2,448.9],[354.5,459.5],[343.9,468.2],[331.8,474.7],[318.7,478.7],[305.0,480.0],[291.3,478.7],[278.2,474.7],[266.1,468.2],[255.5,459.5],[246.8,448.9],[240.3,436.8],[236.3,423.7],[235.0,410.0],[236.3,396.3],[240.3,383.2],[246.8,371.1],[255.5,360.5],[266.1,351.8],[278.2,345.3],[291.3,341.3],[305.0,340.0]]]},"symbol":{"type":"CIMPolygonSymbol","symbolLayers":[{"type":"CIMSolidFill","enable":true,"colorLocked":true,"color":[0,0,0,255]}]}},{"type":"CIMMarkerGraphic","geometry":{"rings":[[[305.0,340.0],[318.7,341.3],[331.8,345.3],[343.9,351.8],[354.5,360.5],[363.2,371.1],[369.7,383.2],[373.7,396.3],[375.0,410.0],[373.7,423.7],[369.7,436.8],[363.2,448.9],[354.5,459.5],[343.9,468.2],[331.8,474.7],[318.7,478.7],[305.0,480.0],[291.3,478.7],[278.2,474.7],[266.1,468.2],[255.5,459.5],[246.8,448.9],[240.3,436.8],[236.3,423.7],[235.0,410.0],[236.3,396.3],[240.3,383.2],[246.8,371.1],[255.5,360.5],[266.1,351.8],[278.2,345.3],[291.3,341.3],[305.0,340.0]]]},"symbol":{"type":"CIMPolygonSymbol","symbolLayers":[{"type":"CIMSolidStroke","enable":true,"colorLocked":true,"capStyle":"Round","joinStyle":"Miter","lineStyle3D":"Strip","miterLimit":10,"width":10,"color":[0,0,0,255]}]}},{"type":"CIMMarkerGraphic","geometry":{"paths":[[[230.0,484.6],[390.5,312.5]]]},"symbol":{"type":"CIMPolygonSymbol","symbolLayers":[{"type":"CIMSolidStroke","enable":true,"primitiveName":"icon_element","capStyle":"Butt","joinStyle":"Miter","lineStyle3D":"Strip","miterLimit":10,"width":9.8292999267578125,"color":[255,255,255,255]}]}},{"type":"CIMMarkerGraphic","geometry":{"paths":[[[221.3,312.5],[381.3,483.9]]]},"symbol":{"type":"CIMPolygonSymbol","symbolLayers":[{"type":"CIMSolidStroke","enable":true,"primitiveName":"icon_element","capStyle":"Butt","joinStyle":"Miter","lineStyle3D":"Strip","miterLimit":10,"width":9.8292999267578125,"color":[255,255,255,255]}]}}],"scaleSymbolsProportionally":true,"respectFrame":true}],"haloSize":1,"scaleX":1,"angleAlignment":"Display"}