{"type":"CIMPointSymbol","symbolLayers":[{"type":"CIMVectorMarker","enable":true,"colorLocked":true,"anchorPointUnits":"Relative","dominantSizeAxis3D":"Z","size":64,"billboardMode3D":"FaceNearPlane","frame":{"xmin":0,"ymin":0,"xmax":612,"ymax":792},"markerGraphics":[{"type":"CIMMarkerGraphic","geometry":{"rings":[[[334.6,351.7],[376.1,393.2],[376.1,452.4],[334.6,493.9],[275.4,493.9],[233.9,452.4],[233.9,393.2],[275.4,351.7],[334.6,351.7]]]},"symbol":{"type":"CIMPolygonSymbol","symbolLayers":[{"type":"CIMSolidFill","enable":true,"color":[255,255,0,255]}]}},{"type":"CIMMarkerGraphic","geometry":{"rings":[[[275.4,493.9],[334.6,493.9],[376.1,452.4],[376.1,393.2],[334.6,351.7],[275.4,351.7],[233.9,393.2],[233.9,452.4],[275.4,493.9]]]},"symbol":{"type":"CIMPolygonSymbol","symbolLayers":[{"type":"CIMSolidStroke","effects":[{"type":"CIMGeometricEffectDashes","dashTemplate":[29.079399108886719,11.847100257873535],"lineDashEnding":"NoConstraint","controlPointEnding":"NoConstraint"}],"enable":true,"capStyle":"Butt","joinStyle":"Miter","lineStyle3D":"Strip","miterLimit":10,"width":10,"color":[0,0,0,255]}]}},{"type":"CIMMarkerGraphic","geometry":{"x":248.772903442382813,"y":394.6167333573103},"symbol":{"type":"CIMTextSymbol","blockProgression":"TTB","depth3D":1,"extrapolateBaselines":true,"fontEffects":"Normal","fontEncoding":"Unicode","fontFamilyName":"Arial","fontType":"Unspecified","haloSize":1,"height":77.544998168945313,"hinting":"Default","horizontalAlignment":"Left","kerning":true,"letterWidth":100,"ligatures":true,"lineGapType":"ExtraLeading","symbol":{"type":"CIMPolygonSymbol","symbolLayers":[{"type":"CIMSolidFill","enable":true,"color":[0,0,0,255]}]},"textCase":"Normal","textDirection":"LTR","verticalAlignment":"Baseline","verticalGlyphOrientation":"Right","wordSpacing":100,"billboardMode3D":"FaceNearPlane"},"textString":"NR"},{"type":"CIMMarkerGraphic","geometry":{"rings":[[[224.0,320.5],[385.6,320.5],[385.6,352.8],[224.0,352.8],[224.0,320.5]]]},"symbol":{"type":"CIMPolygonSymbol","symbolLayers":[{"type":"CIMSolidFill","enable":true,"color":[255,255,0,255]}]}},{"type":"CIMMarkerGraphic","geometry":{"rings":[[[224.0,320.5],[385.6,320.5],[385.6,352.8],[224.0,352.8],[224.0,320.5]]]},"symbol":{"type":"CIMPolygonSymbol","symbolLayers":[{"type":"CIMSolidStroke","enable":true,"capStyle":"Round","joinStyle":"Miter","lineStyle3D":"Strip","miterLimit":10,"width":10,"color":[0,0,0,255]}]}}],"scaleSymbolsProportionally":true,"respectFrame":true}],"haloSize":1,"scaleX":1,"angleAlignment":"Display"}